volbatch/__init__.py
volbatch/data.py
volbatch/transform.py
volbatch/utils.py
volbatch/vol_params.py
volbatch/volbatch.py
volbatch-0.1.2.dist-info/licenses/LICENSE
volbatch-0.1.2.dist-info/METADATA
volbatch-0.1.2.dist-info/WHEEL
volbatch-0.1.2.dist-info/top_level.txt
volbatch-0.1.2.dist-info/RECORD
