Metadata-Version: 2.4
Name: volbatch
Version: 0.1.2
Summary: Generate volatility surface data from option prices and output the results in JSON format.
Home-page: https://github.com/GBERESEARCH/volbatch
Author: GBERESEARCH
Author-email: gberesearch@gmail.com
License: MIT
License-File: LICENSE
Requires-Dist: numpy>=2.2.3
Requires-Dist: pandas>=2.2.3
Requires-Dist: requests>=2.32.3
Requires-Dist: volvisdata>=1.0.9
Requires-Dist: voldiscount>=0.0.2
Dynamic: license-file
